LICENSE.txt
README.md
setup.py
suts/__init__.py
suts/__version__.py
suts.egg-info/PKG-INFO
suts.egg-info/SOURCES.txt
suts.egg-info/dependency_links.txt
suts.egg-info/top_level.txt
suts/lib/__init__.py
suts/lib/flask/__init__.py
suts/lib/flask/flask_session_manage.py
suts/misc/__init__.py
suts/misc/code.py
suts/misc/network.py
suts/misc/url.py