Metadata-Version: 2.1
Name: suts
Version: 0.0.3
Summary: A small example package
Home-page: https://github.com/suanve/suts
Author: suanve
Author-email: suanwell@hotmail.com
Classifier: Programming Language :: Python :: 3
Classifier: License :: OSI Approved :: MIT License
Classifier: Operating System :: OS Independent
Requires-Python: >=3.6
License-File: LICENSE.txt
